{
  "successMap": {
    "0": 63206000,
    "1": 39819780,
    "2": 37981944,
    "3": 31593276,
    "4": 23023440,
    "5": 14549535,
    "6": 7768530,
    "7": 3331251,
    "8": 1034264,
    "9": 177100
  },
  "successMapSum": 222485120,
  "successPercent": {
    "0": "0.28",
    "1": "0.18",
    "2": "0.17",
    "3": "0.14",
    "4": "0.10",
    "5": "0.07",
    "6": "0.03",
    "7": "0.01",
    "8": "0.00",
    "9": "0.00"
  },
  "blockMap": {
    "0": 177100,
    "1": 1034264,
    "2": 3331251,
    "3": 7768530,
    "4": 14549535,
    "5": 23023440,
    "6": 31593276,
    "7": 37981944,
    "8": 39819780,
    "9": 63206000
  },
  "blockMapSum": 222485120
}